{
  "url": "https://docs.limacharlie.io/docs/ext-zeek",
  "title": "Zeek",
  "slug": "ext-zeek",
  "category": "",
  "metadata": {
    "summary": "While it is Free to enable the Zeek extension, pricing is applied to processed PCAPs at a rate of $0.02/GB.",
    "keywords": [
      "add-on",
      "agent",
      "automatic",
      "collection",
      "configuration",
      "d&r",
      "detection",
      "edr",
      "endpoint",
      "event",
      "extension",
      "legacy",
      "manual",
      "migrating",
      "organization"
    ],
    "complexity": "advanced",
    "use_cases": []
  },
  "api_elements": [],
  "content_hash": ""
}