{
  "url": "https://docs.limacharlie.io/docs/adapter-types-canarytokens",
  "title": "Canarytokens",
  "slug": "adapter-types-canarytokens",
  "category": "",
  "metadata": {
    "summary": "Canarytokens can be ingested in LimaCharlie via a Webhook Adapter, and are recognized as the `canary_token` platform.",
    "keywords": [
      "adapter",
      "agent",
      "api",
      "building",
      "canaryalert",
      "canarytokens",
      "configuring",
      "deployment",
      "edr",
      "endpoint",
      "event",
      "initial",
      "integration",
      "limacharlie",
      "organization"
    ],
    "complexity": "intermediate",
    "use_cases": []
  },
  "api_elements": [],
  "content_hash": ""
}