{
  "url": "https://docs.limacharlie.io/docs/false-positive-rules",
  "title": "False Positive Rules",
  "slug": "false-positive-rules",
  "category": "",
  "metadata": {
    "summary": "To reduce the number of false positives, you may want to create false positive (FP) rules. FP rules filter out detections generated by the `report` action of detection & response (D&R) rules. These rules apply globally across all rule namespaces and targets.",
    "keywords": [
      "articles",
      "cases",
      "create",
      "d&r",
      "detection",
      "detections",
      "event",
      "examples",
      "false",
      "ignore",
      "organization",
      "positive",
      "related",
      "response",
      "rule"
    ],
    "complexity": "intermediate",
    "use_cases": [
      "](#use-cases)",
      "The typical use case for FP rules is to add exceptions from some detections that are cross-cutting (for example ignore all detections from a specific host), organization-specific exceptions (like ignoring alerts relating to a custom piece of software used in an organization), or suppressing errors from managed  rules you don't have direct access to."
    ],
    "related_pages": [
      {
        "slug": "detection-and-response",
        "title": "Detection and Response",
        "score": 15
      },
      {
        "slug": "detection-and-response-examples",
        "title": "Detection and Response Examples",
        "score": 14
      },
      {
        "slug": "infrastructure-as-code",
        "title": "Infrastructure as Code",
        "score": 13
      },
      {
        "slug": "stateful-rules",
        "title": "Stateful Rules",
        "score": 13
      },
      {
        "slug": "detection-on-alternate-targets",
        "title": "Detection on Alternate Targets",
        "score": 13
      }
    ]
  },
  "api_elements": [],
  "content_hash": "c7429cca3b25121248c8f170b329613e284f4bc3f2e30251f28e9b12a3c93b4b"
}