{
  "slug": "access-and-permissions",
  "title": "Access and Permissions",
  "category": "",
  "metadata": {
    "summary": "Overview of LimaCharlie's multi-tenant access control using Users, API Keys, and Groups",
    "keywords": [
      "multi-tenant",
      "organization",
      "users",
      "api-keys",
      "groups",
      "permissions"
    ],
    "complexity": "beginner",
    "primary_use_case": "Understanding the access control model and entities in LimaCharlie"
  },
  "extracted_apis": [],
  "cross_refs": [
    {
      "target_slug": "api-keys",
      "relationship": "continuation",
      "description": "API Keys provide programmatic access with permissions defined in this overview"
    },
    {
      "target_slug": "user-access",
      "relationship": "continuation",
      "description": "Detailed instructions for managing user permissions and groups"
    },
    {
      "target_slug": "reference-permissions",
      "relationship": "related",
      "description": "Complete reference of all available permissions mentioned in this overview"
    }
  ]
}