{
  "slug": "ext-cloud-cli-azure",
  "title": "Azure",
  "category": "",
  "metadata": {
    "summary": "Execute Azure CLI commands from LimaCharlie using the Cloud CLI Extension with service principal authentication.",
    "keywords": [
      "azure",
      "cloud-cli",
      "extension",
      "service-principal",
      "virtual-machines"
    ],
    "complexity": "intermediate",
    "primary_use_case": "Manage Azure resources programmatically from LimaCharlie detection and response rules"
  },
  "extracted_apis": [
    {
      "type": "cli_command",
      "method": "extension request",
      "path": "ext-cloud-cli azure",
      "description": "Execute Azure CLI commands via LimaCharlie extension with az vm list example"
    },
    {
      "type": "rest_endpoint",
      "method": "POST",
      "path": "/extension/request",
      "description": "Extension request action to run Azure CLI commands with cloud='az', command_line, and credentials parameters"
    }
  ],
  "cross_refs": [
    {
      "target_slug": "ext-cloud-cli-microsoft365",
      "relationship": "related",
      "description": "Similar cloud CLI extension pattern for Microsoft 365 tenant management, uses same credential secret format (appID/clientSecret/tenantID)"
    }
  ]
}