{
  "slug": "observability-pipeline",
  "title": "Observability Pipeline",
  "category": "",
  "metadata": {
    "summary": "Unified telemetry collection and routing pipeline with bi-directional response capabilities and free data retention",
    "keywords": [
      "observability",
      "telemetry",
      "pipeline",
      "SIEM",
      "data-retention"
    ],
    "complexity": "beginner",
    "primary_use_case": "Build scalable observability pipeline that collects data from any source and routes to any destination with automated response"
  },
  "extracted_apis": [],
  "cross_refs": []
}