{
  "slug": "sleeper-mode",
  "title": "Sleeper Mode",
  "category": "",
  "metadata": {
    "summary": "Pre-deploy sensors across infrastructure that remain dormant until activated for incident response",
    "keywords": [
      "sleeper-mode",
      "incident-response",
      "pre-deployment",
      "cost-efficiency",
      "rapid-activation"
    ],
    "complexity": "intermediate",
    "primary_use_case": "Enable instant visibility during incidents without maintaining full EDR costs on all endpoints"
  },
  "extracted_apis": [],
  "cross_refs": [
    {
      "target_slug": "sleeper",
      "relationship": "continuation",
      "description": "Provides detailed implementation and billing specifics for sleeper mode deployment"
    }
  ]
}